bookspointer/Credentials.json
bookspointer/__init__.py
bookspointer/api.py
bookspointer/categories.json
bookspointer/scraper.py
bookspointer/server.py
bookspointer/sheet.py
bookspointer-0.2.7.dist-info/METADATA
bookspointer-0.2.7.dist-info/WHEEL
bookspointer-0.2.7.dist-info/top_level.txt
bookspointer-0.2.7.dist-info/RECORD
