Metadata-Version: 2.4
Name: bookspointer
Version: 0.2.7
Summary: A package for scraping and serving book data in to bookspointer.
Author-email: Samir Das <samircd4@gmail.com>
License: MIT
Project-URL: Homepage, https://github.com/samircd4
Project-URL: Repository, https://github.com/samircd4/bookspointer
Classifier: Programming Language :: Python :: 3
Classifier: License :: OSI Approved :: MIT License
Classifier: Operating System :: OS Independent
Requires-Python: >=3.7
Requires-Dist: requests
Requires-Dist: selectolax
Requires-Dist: rich
Requires-Dist: python-dotenv
Requires-Dist: gspread
Requires-Dist: google-auth
Requires-Dist: google-auth-oauthlib
Requires-Dist: pandas
